flake8_import_linter
