Metadata-Version: 2.1
Name: flake8-import-linter
Version: 0.1.11
Summary: Flake8 plugin that checks for forbidden imports in your code
Home-page: https://github.com/danmilgram/flake8-import-linter
Author: Dan Milgram
Author-email: ddmilgram@gmail.com
License: MIT
Keywords: flake8 import linter
Platform: UNKNOWN
Classifier: Environment :: Console
Classifier: Framework :: Flake8
Classifier: Operating System :: OS Independent
Classifier: Topic :: Software Development :: Documentation
Classifier: Topic :: Software Development :: Libraries :: Python Modules
Classifier: Topic :: Software Development :: Quality Assurance
Classifier: Programming Language :: Python
